github_subdir_dl/__init__.py
github_subdir_dl/github_subdir_dl.py
github_subdir_dl-0.1.0.dist-info/METADATA
github_subdir_dl-0.1.0.dist-info/WHEEL
github_subdir_dl-0.1.0.dist-info/entry_points.txt
github_subdir_dl-0.1.0.dist-info/top_level.txt
github_subdir_dl-0.1.0.dist-info/RECORD
